texpro/__init__.py
texpro/settings.py
texpro/texassets.py
texpro/utils.py
texpro-0.9.2.dist-info/LICENSE
texpro-0.9.2.dist-info/WHEEL
texpro-0.9.2.dist-info/METADATA
texpro-0.9.2.dist-info/RECORD
