Metadata-Version: 2.1
Name: texpro
Version: 0.9.2
Summary: Create, view and export LaTeX assets (equations, figures, tables, etc.)
Home-page: https://github.com/csemken/texpro/
Author: Christoph Semken
Author-email: christoph.tp@semken.info
Requires-Python: >=3.7
Classifier: License :: OSI Approved :: GNU General Public License v3 or later (GPLv3+)
Requires-Dist: ipython>=6.0
Requires-Dist: jupyter ; extra == "dev"
Requires-Dist: seaborn ; extra == "dev"
Requires-Dist: plotly ; extra == "dev"
Requires-Dist: statsmodels ; extra == "dev"
Requires-Dist: stargazer ; extra == "dev"
Requires-Dist: pdf2image ; extra == "dev"
Requires-Dist: sphinx ; extra == "doc"
Requires-Dist: myst-parser ; extra == "doc"
Requires-Dist: nbsphinx ; extra == "doc"
Requires-Dist: sphinx-rtd-theme ; extra == "doc"
Provides-Extra: dev
Provides-Extra: doc
